{
  "type": "pastel:pedestal",
  "time": 160,
  "tier": "basic",
  "colors": {
    "pastel:cyan": 0,
    "pastel:magenta": 0,
    "pastel:yellow": 0,
    "pastel:black": 0,
    "pastel:white": 0
  },
  "experience": 1.0,
  "pattern": [
    "KVK",
    "AEA",
    "FPF"
  ],
  "key": {
    "V": "pastel:nectered_viognier",
    "F": "pastel:myceylon",
    "K": "pastel:incandescent_essence",
    "A": "pastel:peach_jam",
    "E": "pastel:clotted_cream",
    "P": "pastel:glass_peach"
  },
  "result": {
    "id": "pastel:peaches_flambe",
    "count": 1
  },
  "required_advancement": "pastel:hidden/collect_cookbooks/imperial_cookbook"
}