{
  "type": "spectrum:enchanter",
  "time": 300,
  "required_experience": 100,
  "ingredients": [
    {
      "item": "minecraft:book"
    },
    {
      "item": "spectrum:black_pigment"
    },
    {
      "item": "spectrum:black_pigment"
    },
    {
      "item": "minecraft:chorus_flower"
    },
    {
      "item": "minecraft:ender_pearl"
    },
    {
      "item": "spectrum:black_pigment"
    },
    {
      "item": "spectrum:black_pigment"
    },
    {
      "item": "minecraft:chorus_flower"
    },
    {
      "item": "minecraft:ender_pearl"
    }
  ],
  "result": {
    "id": "minecraft:enchanted_book",
    "components": {
      "stored_enchantments": {
        "spectrum:voiding": 1
      }
    }
  },
  "required_advancement": "spectrum:unlocks/enchantments/voiding_crafting",
  "fabric:load_conditions": [
    {
      "condition": "spectrum:enchantments_exist",
      "values": [
        "spectrum:voiding"
      ]
    }
  ]
}