{
  "type": "pastel:crystallarieum_growing",
  "ingredient": {
    "item": "gobber2:gobber2_globette"
  },
  "growth_stage_states": [
    {
      "Name": "pastel:small_globette_bud",
      "Properties": {
        "facing": "up"
      }
    },
    {
      "Name": "pastel:large_globette_bud",
      "Properties": {
        "facing": "up"
      }
    },
    {
      "Name": "pastel:globette_cluster",
      "Properties": {
        "facing": "up"
      }
    }
  ],
  "seconds_per_growth_stage": 60,
  "ink_color": "pastel:blue",
  "ink_cost_tier": 2,
  "grows_without_catalyst": false,
  "catalysts": [
    {
      "ingredient": {
        "item": "gobber2:gobber2_foo"
      },
      "growth_acceleration_mod": 2.0,
      "ink_consumption_mod": 0.5,
      "consume_chance_per_second": 0.1
    },
    {
      "ingredient": {
        "item": "gobber2:gobber2_foo_nether"
      },
      "growth_acceleration_mod": 4.0,
      "ink_consumption_mod": 0.25,
      "consume_chance_per_second": 0.1
    },
    {
      "ingredient": {
        "item": "gobber2:gobber2_foo_end"
      },
      "growth_acceleration_mod": 8.0,
      "ink_consumption_mod": 0.125,
      "consume_chance_per_second": 0.1
    }
  ],
  "additional_recipe_manager_results": [
    {
      "id": "pastel:pure_globette"
    }
  ],
  "neoforge:conditions": [
    {
      "condition": "pastel:integration_pack_active",
      "integration_pack": "gobber2"
    }
  ]
}