{
  "type": "pastel:pedestal",
  "time": 600,
  "tier": "complex",
  "colors": {
    "pastel:cyan": 0,
    "pastel:magenta": 4,
    "pastel:yellow": 8,
    "pastel:white": 4,
    "pastel:black": 0
  },
  "experience": 2,
  "pattern": [
    "MPM",
    " S ",
    " S "
  ],
  "key": {
    "S": "minecraft:smooth_basalt",
    "M": "pastel:dragonbone_chunk",
    "P": "#pastel:resplendent_feathers"
  },
  "result": {
    "id": "pastel:dragonrending_pickaxe",
    "components": {
      "enchantments": {
        "pastel:razing": 3
      }
    },
    "count": 1
  },
  "required_advancement": "pastel:unlocks/equipment/dragonrending_pickaxe"
}