{
  "type": "pastel:pedestal",
  "group": "colored_saplings",
  "time": 160,
  "tier": "basic",
  "colors": {
    "pastel:cyan": 0,
    "pastel:magenta": 0,
    "pastel:yellow": 6,
    "pastel:white": 0,
    "pastel:black": 0
  },
  "experience": 1.0,
  "pattern": [
    "DDD",
    "VSV",
    "DDD"
  ],
  "key": {
    "S": "#minecraft:saplings",
    "V": "pastel:vegetal",
    "D": "minecraft:yellow_dye"
  },
  "result": {
    "id": "pastel:yellow_sapling",
    "count": 1
  },
  "required_advancement": "pastel:unlocks/colored_saplings/yellow_sapling"
}