{
  "fabric:load_conditions": [
    {
      "type": "pastel:enchantments_exist",
      "values": [
        "minecraft:projectile_protection"
      ]
    }
  ],
  "type": "pastel:enchantment_upgrade",
  "bulk_item": {
    "item": "pastel:pink_pigment"
  },
  "enchantment": "minecraft:projectile_protection",
  "group": "minecraft",
  "item_scaling": {
    "type": "pastel:doubling",
    "scaling_value": 8
  },
  "level_cap": 8,
  "required_advancement": "pastel:unlocks/enchantments/vanilla_protection",
  "xp_scaling": {
    "type": "pastel:indexed",
    "indexes": [
      100,
      200,
      300,
      400,
      800,
      1300,
      2000
    ]
  }
}